odoo/addons/fieldservice_size/README.rst
odoo/addons/fieldservice_size/__init__.py
odoo/addons/fieldservice_size/__manifest__.py
odoo/addons/fieldservice_size/i18n/es.po
odoo/addons/fieldservice_size/i18n/es_AR.po
odoo/addons/fieldservice_size/i18n/fieldservice_size.pot
odoo/addons/fieldservice_size/i18n/it.po
odoo/addons/fieldservice_size/i18n/pt_BR.po
odoo/addons/fieldservice_size/models/__init__.py
odoo/addons/fieldservice_size/models/fsm_location.py
odoo/addons/fieldservice_size/models/fsm_location_size.py
odoo/addons/fieldservice_size/models/fsm_order.py
odoo/addons/fieldservice_size/models/fsm_size.py
odoo/addons/fieldservice_size/readme/CONFIGURE.md
odoo/addons/fieldservice_size/readme/CONTRIBUTORS.md
odoo/addons/fieldservice_size/readme/DESCRIPTION.md
odoo/addons/fieldservice_size/readme/ROADMAP.md
odoo/addons/fieldservice_size/readme/USAGE.md
odoo/addons/fieldservice_size/security/ir.model.access.csv
odoo/addons/fieldservice_size/static/description/icon.png
odoo/addons/fieldservice_size/static/description/icon.svg
odoo/addons/fieldservice_size/static/description/index.html
odoo/addons/fieldservice_size/tests/__init__.py
odoo/addons/fieldservice_size/tests/test_fsm_order.py
odoo/addons/fieldservice_size/views/fsm_location.xml
odoo/addons/fieldservice_size/views/fsm_order.xml
odoo/addons/fieldservice_size/views/fsm_size.xml
odoo/addons/fieldservice_size/views/menu.xml
odoo_addon_fieldservice_size-18.0.1.0.0.6.dist-info/METADATA
odoo_addon_fieldservice_size-18.0.1.0.0.6.dist-info/WHEEL
odoo_addon_fieldservice_size-18.0.1.0.0.6.dist-info/top_level.txt
odoo_addon_fieldservice_size-18.0.1.0.0.6.dist-info/RECORD
